MANIFEST.in
README.md
setup.py
src/masonite/contrib/__init__.py
src/masonite/contrib/essentials/helpers/__init__.py
src/masonite/contrib/essentials/helpers/views/hashid.py
src/masonite/contrib/essentials/middleware/HashIDMiddleware.py
src/masonite/contrib/essentials/middleware/__init__.py
src/masonite/contrib/essentials/providers/HashIDProvider.py
src/masonite/contrib/essentials/providers/__init__.py
src/masonite_essentials.egg-info/PKG-INFO
src/masonite_essentials.egg-info/SOURCES.txt
src/masonite_essentials.egg-info/dependency_links.txt
src/masonite_essentials.egg-info/requires.txt
src/masonite_essentials.egg-info/top_level.txt