Metadata-Version: 2.1
Name: masonite-essentials
Version: 0.0.1
Summary: Essential Features for Masonite
Home-page: https://github.com/MasoniteFramework/essentials
Author: Joseph Mancuso
Author-email: joe@masoniteproject.com
License: MIT
Keywords: masonite,python web framework,python3
Platform: UNKNOWN
Classifier: Development Status :: 3 - Alpha
Classifier: Intended Audience :: Developers
Classifier: Topic :: Software Development :: Build Tools
Classifier: Operating System :: OS Independent
Classifier: License :: OSI Approved :: MIT License
Classifier: Programming Language :: Python :: 3.4
Classifier: Programming Language :: Python :: 3.5
Classifier: Programming Language :: Python :: 3.6
Classifier: Programming Language :: Python :: 3.7
Classifier: Programming Language :: Python :: 3 :: Only
Classifier: Topic :: Software Development :: Libraries :: Application Frameworks
Classifier: Topic :: Software Development :: Libraries :: Python Modules
Provides-Extra: hashids
